simple_gh_aws_creds/__init__.py
simple_gh_aws_creds/_version.py
simple_gh_aws_creds/api.py
simple_gh_aws_creds/impl.py
simple_gh_aws_creds/paths.py
simple_gh_aws_creds/vendor/__init__.py
simple_gh_aws_creds/vendor/pytest_cov_helper.py
simple_gh_aws_creds-0.1.1.dist-info/AUTHORS.rst
simple_gh_aws_creds-0.1.1.dist-info/LICENSE.txt
simple_gh_aws_creds-0.1.1.dist-info/METADATA
simple_gh_aws_creds-0.1.1.dist-info/WHEEL
simple_gh_aws_creds-0.1.1.dist-info/RECORD
