Metadata-Version: 2.3
Name: simple_gh_aws_creds
Version: 0.1.1
Summary: Simple Python library to quickly set up AWS credentials for GitHub Actions without complex OIDC configuration.
License: MIT
Author: Sanhe Hu
Author-email: husanhe@email.com
Maintainer: Sanhe Hu
Maintainer-email: husanhe@email.com
Requires-Python: >=3.9,<4.0
Classifier: License :: OSI Approved :: MIT License
Classifier: Programming Language :: Python :: 3
Classifier: Programming Language :: Python :: 3.9
Classifier: Programming Language :: Python :: 3.10
Classifier: Programming Language :: Python :: 3.11
Classifier: Programming Language :: Python :: 3.12
Classifier: Programming Language :: Python :: 3.13
Provides-Extra: auto
Provides-Extra: dev
Provides-Extra: doc
Provides-Extra: test
Requires-Dist: PyGithub (>=2.1.1,<3.0.0)
Requires-Dist: Sphinx (>=7.4.7,<8.0.0) ; extra == "doc"
Requires-Dist: boto3 (>=1.35.0,<2.0.0)
Requires-Dist: boto_session_manager (>=1.0.0,<2.0.0) ; extra == "test"
Requires-Dist: build (>=1.2.1,<2.0.0) ; extra == "dev"
Requires-Dist: docfly (==3.0.0) ; extra == "doc"
Requires-Dist: furo (==2024.8.6) ; extra == "doc"
Requires-Dist: home_secret (>=0.1.1,<1.0.0) ; extra == "test"
Requires-Dist: ipython (>=8.18.1,<8.19.0) ; extra == "doc"
Requires-Dist: moto (>=5.0.0,<6.0.0) ; extra == "test"
Requires-Dist: nbsphinx (>=0.8.12,<1.0.0) ; extra == "doc"
Requires-Dist: pygments (>=2.18.0,<3.0.0) ; extra == "doc"
Requires-Dist: pytest (>=8.2.2,<9.0.0) ; extra == "test"
Requires-Dist: pytest-cov (>=6.0.0,<7.0.0) ; extra == "test"
Requires-Dist: rich (>=13.8.1,<14.0.0) ; extra == "dev"
Requires-Dist: rstobj (==1.2.1) ; extra == "doc"
Requires-Dist: sphinx-copybutton (>=0.5.2,<1.0.0) ; extra == "doc"
Requires-Dist: sphinx-design (>=0.6.1,<1.0.0) ; extra == "doc"
Requires-Dist: sphinx-jinja (>=2.0.2,<3.0.0) ; extra == "doc"
Requires-Dist: twine (>=6.0.0,<7.0.0) ; extra == "dev"
Requires-Dist: wheel (>=0.45.0,<1.0.0) ; extra == "dev"
Project-URL: Changelog, https://github.com/MacHu-GWU/simple_gh_aws_creds-project/blob/main/release-history.rst
Project-URL: Documentation, https://simple-gh-aws-creds.readthedocs.io/en/latest/
Project-URL: Download, https://pypi.org/pypi/simple-gh-aws-creds#files
Project-URL: Homepage, https://github.com/MacHu-GWU/simple_gh_aws_creds-project
Project-URL: Issues, https://github.com/MacHu-GWU/simple_gh_aws_creds-project/issues
Project-URL: Repository, https://github.com/MacHu-GWU/simple_gh_aws_creds-project
